speech_to_text/__init__.py
speech_to_text/command.py
speech_to_text/config.py
speech_to_text/formatters.py
speech_to_text/utils.py
speech_to_text-0.1.0.data/scripts/main.py
speech_to_text-0.1.0.dist-info/DESCRIPTION.rst
speech_to_text-0.1.0.dist-info/METADATA
speech_to_text-0.1.0.dist-info/RECORD
speech_to_text-0.1.0.dist-info/WHEEL
speech_to_text-0.1.0.dist-info/dependency_links.txt
speech_to_text-0.1.0.dist-info/entry_points.txt
speech_to_text-0.1.0.dist-info/metadata.json
speech_to_text-0.1.0.dist-info/top_level.txt
speech_to_text-0.1.0.dist-info/zip-safe
